matplotlib_venn_wordcloud/__init__.py
matplotlib_venn_wordcloud/_main.py
matplotlib_venn_wordcloud/examples.py
matplotlib_venn_wordcloud-0.2.6.dist-info/LICENSE
matplotlib_venn_wordcloud-0.2.6.dist-info/METADATA
matplotlib_venn_wordcloud-0.2.6.dist-info/WHEEL
matplotlib_venn_wordcloud-0.2.6.dist-info/top_level.txt
matplotlib_venn_wordcloud-0.2.6.dist-info/RECORD
